fairseq/__init__.py
morphologicaldecomposer/__init__.py
morphologicaldecomposer/add_eos.py
morphologicaldecomposer/merge.py
ukuxhumana/__init__.py
ukuxhumana/clean_data.py
ukuxhumana/compress_datasets_for_t2t.py
ukuxhumana/create_bpe.py
ukuxhumana/create_fastText.py
ukuxhumana/t2t/__init__.py
ukuxhumana/t2t/t2t_enaf_problem.py
ukuxhumana/t2t/t2t_ennso_problem.py
ukuxhumana/t2t/t2t_entn_problem.py
ukuxhumana/t2t/t2t_ents_problem.py
ukuxhumana/t2t/t2t_enzu_bpe_problem.py
ukuxhumana/t2t/t2t_enzu_problem.py
ukuxhumana/t2t/t2t_evaluate_model.py
ukuxhumana/t2t/t2t_problem.py
ukuxhumana/t2t/problems/__init__.py
ukuxhumana/t2t/problems/translate_enaf.py
ukuxhumana/t2t/problems/translate_ennso.py
ukuxhumana/t2t/problems/translate_entn.py
ukuxhumana/t2t/problems/translate_ents.py
ukuxhumana/t2t/problems/translate_enzu.py
ukuxhumana-0.0.1.dist-info/LICENSE.md
ukuxhumana-0.0.1.dist-info/METADATA
ukuxhumana-0.0.1.dist-info/WHEEL
ukuxhumana-0.0.1.dist-info/top_level.txt
ukuxhumana-0.0.1.dist-info/RECORD
