Metadata-Version: 2.1
Name: ukuxhumana
Version: 0.0.1
Summary: Neural Machine Translation for African Languages
Home-page: https://github.com/LauraMartinus/ukuxhumana
Author: Laura martinus,Jade Abbott
Author-email: jabbott@retrorabbit.co.za
License: gpl-3.0
Keywords: neural machine translation african languages
Platform: UNKNOWN
Requires-Dist: tensor2tensor
